[
    {
        "Title": "[問卦] 為何無套幹屁眼得愛滋是別人的錯？", 
        "Author": "sa99", 
        "UpVote": 3, 
        "NoVote": 7, 
        "Content": "\n甲甲們無套亂肛 雜交 吸毒no掉亂肛\n然後申裝了就變成別人的錯\n\n大喊Hiv ok!\n\n不支持 就是歧視、反同\n\n然後歧視會隔空傳染 是社會的錯\n\n這4什麼樣的概念？\n\n\n\n\n_ _\n\n", 
        "DownVote": 5
    }, 
    {
        "Title": "Re: [新聞] 台大女慘被卸7塊　狠男母：兒立志從警", 
        "Author": "arrenwu", 
        "UpVote": 12, 
        "NoVote": 27, 
        "Content": ":\n", 
        "DownVote": 0
    }, 
    {
        "Title": "Re: [新聞] 95才28.4元？ 館長譏段宜康「民間疾苦4字", 
        "Author": "jacklyl", 
        "UpVote": 9, 
        "NoVote": 5, 
        "Content": "\n\n政治人物就垃圾阿\n\n活該\n\n民粹就是這樣\n\n明知道是正常狀況還要罵還要酸\n\n等到自己執政時再被打臉\n\n\n明知道誰執政都換斷交 還要罵\n\n現在嘗苦果\n\n\n明知道誰執政都有可能油電雙漲 還要罵\n\n現在被反罵剛好而以\n\n\n反而是要密切觀察KMT\n\n如果跟風罵斷交 罵漲價 那這個黨以後也繼續等著被反酸吃屎\n\n\n台灣的政治人物除了柯P以外\n\n每個都在昧著良心說話 人民還跟著起舞\n\n以前跟著DPP 現在跟著KMT 真是悲哀\n\n--\n", 
        "DownVote": 3
    }, 
    {
        "Title": "[問卦] 氣候與刑案有無關聯性？", 
        "Author": "linchaoyang", 
        "UpVote": 3, 
        "NoVote": 13, 
        "Content": "\n\n最近台中 新北 陸續發生震驚社會的命案\n\n除了嫌犯具有罹患心理疾病的特徵外\n\n天氣也是十分的炎熱\n\n所以我在想啊！\n\n氣候溫度與兇殺刑案是否有相關聯性？\n\n本來想Google「天氣與刑案」\n\n但找不到什麼資料…\n\n不知道版上是否有犯罪防治學系專業的鄉民\n能提供看法啊？\n\n好久都沒有優質專業的文章了\n小弟在這回合覆蓋一張問卦額度 結束此回合\n希望能召喚出八卦版「刑事犯罪研究王」\n\n--\n", 
        "DownVote": 1
    }, 
    {
        "Title": "[問卦] 這是什麼蟲?", 
        "Author": "NanaIS", 
        "UpVote": 7, 
        "NoVote": 2, 
        "Content": "\n是這樣的，小妹剛剛不小心踩到了硬硬的東西，\n\n結果發現是隻蟲蟲，查了一下，好像不是很夯的荔枝椿象，\n\n有人知道這是什麼蟲嗎？謝謝。\n\n", 
        "DownVote": 3
    }, 
    {
        "Title": "[新聞] 薪資增加難追房價 台北連三個月價量俱跌", 
        "Author": "sayt5943", 
        "UpVote": 10, 
        "NoVote": 3, 
        "Content": "\n聯合\n\n薪資增加難追房價 台北連三個月價量俱跌\n\n好時價公布最新房價指數，今年1月全台房價指數120，已連續10個月上揚，不過台北市表\n現仍差，和去年同期相比，已連續三個月價量俱跌，目前北市房價回到2013年水準，較高\n點回跌約一成。\n\n好時價分析，台北市房價雖有修正，民眾卻超無感，交易量一直在低檔，主要是先前房價\n漲太快，台北人薪資所得雖有增加，還是買不起。\n\n根據好時價統計相關資料，自2008年1月至2018年1月，10年間台北市家庭可支配所得從12\n8.6萬元上升至133.9萬元，10年增加僅4.1%，但同時間，台北市信義房價指數從66.59大\n增到114.58，成長幅度達72.1%，兩者成長率差距高達18倍。\n\n好時價以實價登錄資料為基礎，透過機器學習估價技術、重複交易法進行分析，每月製作\n全台及各行政區房價指數。\n\n根據好時價房價指數，今年1月全台指數重新站上120，已連續10月微幅上揚，較去年3月\n的低點上升約2.4%。\n\n以區域來看，新北、台中、台南及高雄同步價量俱漲，其中又以台南表現較佳。桃園1月\n為價跌量增，台北市和去年同期相比，已連續三個月呈現價量俱跌。\n\n好時價分析，儘管好時價台北市房價指數在2015年中開始下跌，甚至目前已跌回2013年的\n水準，但在所得近乎無成長之情況下，民眾依舊難以負擔此時房價，房價修正因此無法引\n起民眾共鳴。\n\n", 
        "DownVote": 5
    }, 
    {
        "Title": "[問卦] 有沒有印度工程師好不好相處的八卦", 
        "Author": "ooooops1221", 
        "UpVote": 20, 
        "NoVote": 11, 
        "Content": "\n今天小妹去竹科面試暑期實習生\n\n主管提到如果進來後會\n跟兩位印度理工的同事合作\n機器學習相關的比賽事宜\n\n之前聽學長說過印度同事雞掰難相處的\n所以魯妹想問有沒有印度工程師好不好相處的卦\n\n\n--\n", 
        "DownVote": 0
    }, 
    {
        "Title": "Re: [問卦] 男人不壞 女人不愛是真的嗎?", 
        "Author": "feedback", 
        "UpVote": 4, 
        "NoVote": 20, 
        "Content": "\n不是\n\n一個人是由很多種特質構築出來的\n\n能夠吸引女性的特質\n\n如：\n幽默風趣\n帥\n有錢\n有想法\n能給人安全感（物質、心理、生理...）\n能跟女生聊得來\n能逗女生開心\n能讓女生不爽卻還是會跟他講話\n......\n等各種正面特質\n\n以上種種特質\n\n你不必是壞男人才有辦法擁有\n\n會那樣覺得\n\n是倒果為因了\n\n\n鄉民所謂的壞\n\n指的大多是\n\n始亂終棄\n用情不專\n小混混\n脾氣差\n各種不良習慣\n.........\n等各種負面特質\n\n如果拼命學習以上特質\n\n想當個壞男人\n\n別說異性朋友\n\n說不定連一般朋友都交不到\n\n\n\n一個人由各種特質組成\n\n看到一個人的負面特質\n\n想著女生為什麼會喜歡上那種人\n\n卻沒想過對方可能有自己不知道的\n\n能吸引女生的特質\n\n只把原因總結成男人不壞女人不愛\n\n這是很可惜的事\n\n\n男人不壞女人不愛\n\n是倒果為因的說法\n\n別被騙了\n\n--\n", 
        "DownVote": 0
    }, 
    {
        "Title": "[問卦] 唐伯虎點秋香，台詞裡面的疑點???", 
        "Author": "KEPPGO", 
        "UpVote": 1, 
        "NoVote": 11, 
        "Content": "\n\n電影唐伯虎點秋香，\n\n\n有一段華安VS對穿腸的台詞\n\n一直感覺英文翻譯中文怪怪的\n\n\n鶯鶯燕燕翠翠紅紅處處融融洽洽\n\n為什麼下面翻譯成英文變成：\n\nａａｂｂｃｃｄｄｅｅｆｆｇｇ\n\n\n會不會讓外國朋友覺得\n\n中國文學很白痴啊？！\n\n\n--\n", 
        "DownVote": 2
    }, 
    {
        "Title": "[問卦] 能有今天的台灣  誰的貢獻比較大?", 
        "Author": "zxasqw0246", 
        "UpVote": 10, 
        "NoVote": 13, 
        "Content": "\n台灣\n\n我們的島嶼\n\n島上有各種不同的聲音\n\n不同的產業\n\n\n曾經的台灣只是塊彈丸之地\n\n沒有文化  沒有經濟\n\n\n但如今\n\n我們至少算是亞洲還不錯的地方了\n\n\n能有今天的台灣\n\n誰的貢獻比較大呢?\n\n\n\n\n(1)  美國爸爸的保護\n\n        美國爸爸在二戰後在背後坦著台灣\n\n        韓戰 還送了物資\n\n        如果沒有美國  我們可能一大堆資源都拿來搞軍事\n\n        然後沒空搞經濟  還可能被中國5筒\n\n\n(2)  中國不溫不吐的五筒\n\n        中國雖然說要統治台灣\n\n        可是已經說了好多年了\n\n        如果中國真的舉家開戰\n\n        肯定沒有現在的台灣島\n\n(3)  日本統治留下來的基礎\n\n        這大家都知道了\n\n        下水道阿 糖廠阿\n\n        還有一些出口產業\n\n        都在日本統治下打下基礎建設\n\n(4)  逮丸郎自己的努力\n\n        經濟起飛時期\n\n        大家努力賺錢\n\n        家庭即手工廠\n\n        無良商人為賺錢\n\n        汙染永續都不管\n\n        全台努力拚經濟\n\n\n\n\n\n大家覺得能有今天的台灣\n\n哪個原因最大呢?\n\n\n\n有沒有八卦?\n\n我ˇ很ˇ好ˋ奇ˊ欸ˋ\n\n--\nPTTlogo板  唯一支持zxasqw0246\n", 
        "DownVote": 1
    }, 
    {
        "Title": "[新聞] 西門町版兩岸國旗一家親？ 警：避免激化", 
        "Author": "sakura000", 
        "UpVote": 16, 
        "NoVote": 12, 
        "Content": "\n自由\n\n西門町版兩岸國旗一家親？ 警：避免激化群眾\n\n〔記者王冠仁／台北報導〕有網友在臉書上發文，指稱昨天下午在台北市西門町看到警察\n將中華民國國旗，與統派團體愛國同心會帶來的中國五星旗插在一起，直呼「柯文哲指揮\n北市警上演兩岸一家親？」對此，萬華分局表示，過去曾有意識形態不同的群眾覺得五星\n旗「太刺眼」與愛國同心會成員發稱衝突，警方為阻止類似情況發生，才派人插國旗以和\n緩兩派群眾情緒。\n\n網友Jessie Huang昨晚在臉書上發文，聲稱在西門町看到「中華旗」與「五星旗」莫名其\n妙的搭配展示宣揚兩岸統一，沒想到晚上收工時，居然直擊前面一輛台北市警車在幫收中\n華旗與五星旗，後面那台是「礙國銅鋅會」（應指愛國同心會）的車子，兩造聯合演出「\n兩岸一家親」大戲？\n\n網友質疑，難不成是警察「吃飽太閒」，熱心幫助統派收隊？或是上級長官指示協助？\n\n萬華分局今天回應指出，昨天愛國同心會在西門町捷運站6號出口後方廣場合法申請集會\n遊行，而插五星旗屬於表達言論自由的範圍，警方無權介入要求他們不要插五星旗。不過\n，以往曾有意識形態與愛國同心會相左的群眾對其叫罵、對嗆，警方為避免衝突發生，才\n會派員插旗，希望意識形態不同的兩造雙方能夠情緒和緩。\n\n此外，警方昨天早上9點多，在愛國同心會成員到場前，就以改道牌在其申請的區域圍成\n隔離區，並將中華民國國旗插在改道牌外。昨早10點愛國同心會到場後，是將五星旗插在\n隔離區內。愛國同心會活動結束後，警方並沒幫忙收五星旗，而是將警方只收拾中華民國\n國旗與改道牌。\n\n萬華分局還說，第一次插國旗是在今年3月，昨天則是第二次使用此方式，每次使用的國\n旗約30面；除了插國旗外，在愛國同心會成員集會期間，警方派員全程蒐證、監控，避免\n衝突行為發生。\n\n", 
        "DownVote": 3
    }, 
    {
        "Title": "Re: [問卦] 你有千枚核彈 你想丟哪國？", 
        "Author": "garko", 
        "UpVote": 6, 
        "NoVote": 7, 
        "Content": "\n開船去外海\n然後丟自己\n\n除了核彈\n有任何方法能瞬間無痛的讓自己離開人世嗎？\n跳樓會怕高，上吊也是會痛，農藥會折磨至死\n燒碳若沒死成，會生不如死，而且若不小心火災，會賠死\n\n羨慕能被核彈炸死的人\n\n--\n", 
        "DownVote": 1
    }, 
    {
        "Title": "[新聞] 美國新國防授權法參眾院出爐 直指中共", 
        "Author": "sunbysea", 
        "UpVote": 22, 
        "NoVote": 19, 
        "Content": "\n影片新聞\n", 
        "DownVote": 0
    }, 
    {
        "Title": "[問卦] 台灣吸毒的人口是不是比想像中多很多？", 
        "Author": "lmfao", 
        "UpVote": 6, 
        "NoVote": 11, 
        "Content": "\n如題\n\n其實多少都會聽到左鄰右舍在八卦社區裡的鄰居\n\n那個誰家的誰誰誰半夜都在吸毒...\n\n跑去偷別人東西鬧事幹嘛的\n\n但其實被他們說的那些鄰居表面上看起來好好的\n\n只是面容有些小憔悴而已\n\n所以有時候在想 路上人來來往往\n\n但實際上有在碰毒的人感覺好像不少\n\n尤其是有些看臉就看得出來了\n\n到底台灣吸毒的人口是不是比你我想像的還多啊？\n\n--\n", 
        "DownVote": 2
    }, 
    {
        "Title": "Re: [問卦] 新北板橋是怎樣的地方？", 
        "Author": "HateAnus", 
        "UpVote": 7, 
        "NoVote": 6, 
        "Content": "\n新板特區超棒啊\n\n房價落在50萬/坪附近\n\n同價位在台北大概只能買萬華吧\n\n但是板橋車站有捷運、台鐵和高鐵\n\n離台北很近\n\n附近生活機能也非常好\n\n所以在台北買不起房\n\n板橋會是個買房子的好地方\n\n\n--\n", 
        "DownVote": 0
    }, 
    {
        "Title": "Re: [新聞] 柯P遭檢舉財產不明　監察院：正等檢舉人", 
        "Author": "Fongin", 
        "UpVote": 1, 
        "NoVote": 1, 
        "Content": "\n\n\n\n阿孟主導的監察院??\n\n黑人問號??\n\n阿孟何時變監察院長了?\n\n\n\n2014馬19提名16人監委\n\n2018小英才補提名11人\n\n監察院DPP並未過半\n\n監察院長還是馬提名的人\n\n\n\n題外話\n\n這屆監察委員任期6年 2014-2020\n\n比小英總統任期4年還長\n\n\n--\n台湾首相の「台湾は独立国家」発言\n\n「台湾の未来は２３００万の台湾住民決定」\n\n", 
        "DownVote": 2
    }, 
    {
        "Title": "[問卦] 只怪我們愛的那麼洶湧", 
        "Author": "silentknight", 
        "UpVote": 1, 
        "NoVote": 4, 
        "Content": "\n\n蹦啾 妹魯喜 波納佩梯\n\n學弟跟女朋友分手後 整個心情低落 不去上課 不接觸人\n\n基於直屬學長學弟情 我去看他一下 順便找他吃飯走走\n\n我問他 不過是分手而已 幹嘛把自己弄成這樣\n\n學弟回答 : 學長你不懂 只怪我們愛得那麼洶湧愛得那麼深\n           於是夢醒了擱淺了沉默了揮手了卻回不了神\n\n\n要怎麼安慰失戀的學弟啊 ?? 天涯何處無芳草 女人在找就有了\n\n--\n\n                   今晚你選那一個姿勢??\n\n  ○       \"○   ○\"       ○\"\n (|\\       (|\\   ))        ))   ○╭○rz    ○rz   ○rz-st○\n /`○rz    /`○r27\\\"   ○r27\\\"   ￣′       ○=^\n\n--\n", 
        "DownVote": 3
    }, 
    {
        "Title": "[新聞] 大陸機師月薪30萬爆增至78萬起跳 引爆跳", 
        "Author": "ilyj2012", 
        "UpVote": 8, 
        "NoVote": 6, 
        "Content": "\n大陸機師月薪30萬爆增至78萬起跳 引爆跳槽風\n\n", 
        "DownVote": 2
    }, 
    {
        "Title": "[問卦] 最簡單的工程 品質工程", 
        "Author": "chamge7788", 
        "UpVote": 0, 
        "NoVote": 2, 
        "Content": "\n你好大家好我是chamge7788\n\n工程和管理是區分開來的 管理嘴吧說說\n\n工程用證明來進行解說\n\n回到正題 我阿最近發現到工程只要是工程數學往往會比較多\n\n是因為要證明而不是嘴砲的管理\n\n但是我很少看過某科管理和工程基本上都已經是難度差不多了\n\n品質工程和品質管理 都是統計學衍生而來的\n\n財務管理和財務工程難度差了很多\n\n而品質管理和品質工程難度卻差不多\n\n工程系列中最簡單的是品質工程嗎?\n\n有沒有品質工程的卦\n\n--\n", 
        "DownVote": 0
    }
]