[
    {
        "Title": "[問卦] 近距離容易看到瑕疵？(毛毛象陣線文)", 
        "Author": "zouelephant", 
        "UpVote": 25, 
        "NoVote": 22, 
        "Content": "\n各位鄉民近期還好嗎 我是毛毛象\n\n有的影片會避免拍攝臉部特寫\n\n其實就是因為臉上有斑 有皺紋 有痘痘\n\n遠拍加上不怎樣的解析度 就可以蒙混過關\n\n以下幾張圖特別使用近距離高解析\n\n希望可以突破這種歪風\n\n", 
        "DownVote": 8
    }, 
    {
        "Title": "[問卦] 被女友發現不是處男會怎樣嗎??", 
        "Author": "ha3810996", 
        "UpVote": 2, 
        "NoVote": 5, 
        "Content": "\n有些人會因為女友欺騙是處女\n\n但後來發現不是而7PUPU\n\n身為非自願性處男，\n\n如果將來交了女朋友，\n\n結果後來被發現已經被左手破處了，\n\n會不會引來殺機啊??!!\n\n--\n", 
        "DownVote": 6
    }, 
    {
        "Title": "[問卦] 交友軟體的霸主是哪個?", 
        "Author": "Beanoodle", 
        "UpVote": 10, 
        "NoVote": 10, 
        "Content": "\n大家安安\n\n乳提\n\n之前有上過新聞的交友軟體\n\n好像逼透可蠻多次的\n\n現在又多了聽的\n\n感覺要交朋友可以優先考慮逼透可\n\n聽的也有耳聞還不錯\n\n\n不過交友軟體現在還蠻多種的\n\n除了這兩款還有哪些熱門的嗎?\n\n霸主會是逼透可嗎?\n\n--\n", 
        "DownVote": 2
    }, 
    {
        "Title": "Re: [問卦] 台語歌這樣唱沒市場？", 
        "Author": "todao", 
        "UpVote": 1, 
        "NoVote": 0, 
        "Content": "\n\n很好聽啊這首，當然有市場。\n\n但因為台語文創早年被打壓(詳見管仁健管大專文)，導致台語歌不被鼓勵走流行路線已經\n很多年了，所以在那時候(無法度按捺是1995年的歌曲)，這種曲風仍是台語歌裡的少數族\n群。\n\n但就如前面說的，好聽的歌當然有市場，所以新型曲風的台語歌從林強在1990年《向前走\n》打破悲情路線後，其實一直都有音樂人在創作，只是一般人只接觸國語歌，不知道而已\n。\n\n像1992年，由當時很紅的港星周慧敏在《流言》專輯裡收錄的新型曲風台語歌《講不出嘴\n》，也絕對是會讓人重複循環的歌，可惜水管找不到了。\n\n又像2000年孟庭葦的《愛到史艷文》台語專輯，裡面一堆很好聽的非傳統曲風台語歌，如\n《故作浪漫》，是由陳冠倩老師作詞作曲，黃韻玲老師編曲：\n", 
        "DownVote": 0
    }, 
    {
        "Title": "Re: [問卦] 館長歧視非洲人？？？", 
        "Author": "AzurElsa", 
        "UpVote": 11, 
        "NoVote": 12, 
        "Content": "\n館長真的不用意外\n\n自己22K徵美編\n\n結果靠北現在年輕人沒未來低薪\n\n這種自打臉到這樣的\n\n我還真的蠻佩服的....\n\n--\n", 
        "DownVote": 6
    }, 
    {
        "Title": "[問卦] 有蔡瑛紋的八卦嗎？", 
        "Author": "Lawleit", 
        "UpVote": 6, 
        "NoVote": 7, 
        "Content": "\n英文名字是Verna\n\n三圍32d 25 34\n\n牡羊座a型\n\n跟蔡英文差了40歲\n\n但年輕的已生過\n\n老的還沒有\n\n有沒有蔡瑛紋的八卦\n\n\n\n-----\nSent from JPTT on my HTC_U-3u.\n\n--\n", 
        "DownVote": 5
    }, 
    {
        "Title": "[問卦] 人道精神是什麼？有屁用嗎？", 
        "Author": "LOLI5566", 
        "UpVote": 12, 
        "NoVote": 44, 
        "Content": "\n\n台灣自己都顧不好自己了\n\n幹嘛還要花錢去就那些窮鬼\n\n反正那些窮鬼國家\n\n多一個人 少一個人 乾我屁事啊\n\n幹嘛浪費這個錢\n\n？\n\n\n\n--\n", 
        "DownVote": 1
    }, 
    {
        "Title": "[問卦] 30破產35離婚40失業 誰慘", 
        "Author": "Kwame", 
        "UpVote": 22, 
        "NoVote": 34, 
        "Content": "\n30歲因投資失敗破產還欠了200萬負債\n\n35歲因戴綠帽離婚一小孩監護權還被拿走\n\n40歲原本年收100多但公司重組被裁員\n\n——————————————————-\n\n這3個誰慘啊？\n\n--\n", 
        "DownVote": 5
    }, 
    {
        "Title": "[問卦] 不能實施人造雨嗎？", 
        "Author": "hwsbetty", 
        "UpVote": 7, 
        "NoVote": 20, 
        "Content": "\n文組小妹路過。\n\n天氣熱到真的讓人覺得很阿雜。\n\n平地不下雨就算了，水庫/集水區不下怎麼辦?\n幾乎每個水庫都可以見底了！\n小妹可不想過沒水沒電的日子啊！\n以前缺水時候，偶會聽到新聞說實施人造雨，這次怎麼好像都安靜無聲?\n不能只仰賴說梅雨可能會來吧？\n而且目前的預報似乎是傾向沒雨啊！\n\n缺水的事情迫在眉睫，難道目前的天候也不利實施人造雨嗎？\n還是根本沒幫助呢？\n\n--\n", 
        "DownVote": 2
    }, 
    {
        "Title": "Re: [問卦] 檢察官沒女友是不是很稀奇", 
        "Author": "kaka7788", 
        "UpVote": 5, 
        "NoVote": 10, 
        "Content": "\n說得太好了!!!\n\n看看檢察總長幫蘇炳坤提起四次非常上訴都被法官駁回\n新竹地檢署檢察官也幫忙提起四次再審 也通通被駁回\n\n蕭明岳案這麼冤 聲請提出這麼多次非常上訴 也通通被最高檢駁回\n現在好不容易台中高檢署檢察官要幫忙提出再審\n應該也會被駁回 法官哪會面對自己的錯誤阿~~~\n\n開庭的時候看見有錢人請的大律師是自己以前的大學同學 在高點的同桌\n司訓所的同學 實習時候的同事 當庭直接要大律師寫的狀紙電子檔 判決書直接複製貼上\n\n果然是近親繁殖 顆顆\n\n前幾天聽某道長說蕭明岳案的那位教唆作偽證的檢察官還想告我們這些網友\n說我們誹謗他 但是他不敢提告~怕一告之後 大家都知道他是誰\n不過現在監察院也已經在查這位檢察官了 但大概記過就沒事了\n\n--\n→ aa52189: 樓下obov我吃屎                                         11/28 00:26\n→ obov: ok\n\n--\n", 
        "DownVote": 1
    }, 
    {
        "Title": "Re: [新聞] 南部〉快見底了 曾文水庫蓄水率剩5％", 
        "Author": "ray198776329", 
        "UpVote": 3, 
        "NoVote": 6, 
        "Content": "\n唉，神父我錯了我需要跟你懺悔，\n2016的那一夜，我真的被騙了！\n真相兩年就越辨越明，\n我以後還是想多看看碧海藍天，\n起碼會治國多了國泰民安，\n現在我真的好後悔啊！請您原諒我\n\n--\n", 
        "DownVote": 6
    }, 
    {
        "Title": "Re: [新聞] 南部〉快見底了 曾文水庫蓄水率剩5％", 
        "Author": "kusomanfcu", 
        "UpVote": 2, 
        "NoVote": 3, 
        "Content": "\n是不是該發動\n\n一人一泡尿到曾文水庫旁的樹下\n\n\n經過天然濾水\n\n水庫就有水嘞\n\n\n", 
        "DownVote": 1
    }, 
    {
        "Title": "Re: [新聞] 南部〉快見底了 曾文水庫蓄水率剩5％", 
        "Author": "inrain", 
        "UpVote": 2, 
        "NoVote": 11, 
        "Content": "\n\n\n南部不下雨是在靠北什麼\n不是幸福城市\n得票率爆幹高\n瞧不起鳥籠國\n阿現在沒下雨就在靠北\n不會井喝地下水逆\n\n\n\n\n--\n", 
        "DownVote": 1
    }, 
    {
        "Title": "[問卦] 鄉民是不是很好操弄？", 
        "Author": "Dinenger", 
        "UpVote": 22, 
        "NoVote": 29, 
        "Content": "\n隨便幾個帳號帶一帶風向\n見獵心喜的就上當了\n還敢笑低卡低能…\n\n我看是半斤八兩\n真不知道哪來的自信？\n\n--\n", 
        "DownVote": 5
    }, 
    {
        "Title": "[問卦] 高譚跟台灣的差別", 
        "Author": "tree8787", 
        "UpVote": 2, 
        "NoVote": 3, 
        "Content": "\n在台灣活也有一陣子啦，遇到大部分都是暖心好人（商人）\n\n哪像高譚只有黑暗以及犯罪\n\n小姐姐疑惑活在哪裡比較好呢？\n\noh。btw 高譚是市、台灣是國\n\n--\n", 
        "DownVote": 1
    }, 
    {
        "Title": "[問卦] 大膽！跟遙香在草地上野戰！(戰女陣線)", 
        "Author": "muscatsss", 
        "UpVote": 5, 
        "NoVote": 2, 
        "Content": "\n安安，大家好\n\n終於到了這個時刻了\n\n夫妻嘛~相處久了就會想要嚐點新事物…\n\n這一次難得", 
        "DownVote": 6
    }, 
    {
        "Title": "[問卦] 有沒有Chrissy Costanza的八卦?", 
        "Author": "tim121507", 
        "UpVote": 2, 
        "NoVote": 4, 
        "Content": "\nChrissy Costanza\n\nAgainst the Current樂團的主唱\n\n早期翻唱的歌曲時候\n\n", 
        "DownVote": 2
    }, 
    {
        "Title": "Re: [問卦] 八卦板什麼時候開始走下坡的？", 
        "Author": "Galvus", 
        "UpVote": 1, 
        "NoVote": 4, 
        "Content": "好像是在2015年6月還是7月開始\n\n八卦版、甚至是整個批踢踢\n\n就開始走下坡了\n\n主要是因為在2014年11月29日\n\n台北市長選舉，柯文哲大勝連勝文\n\n讓許許多多的媒體業者，開始注意起批踢踢這個平台\n\n讓很多勢力進入批踢踢\n\n然後從那一天起剛好算起來半年左右\n\n批踢踢的整個風氣就改變了\n\n專業文被狂噓\n\n惡意帶風向文被推爆\n\n結果就是讓許多專業人士\n\n紛紛離開批踢踢\n\n跳槽到FaceBook私密社團\n\n或是Dcard去分享真實經歷\n\n這就是典型的劣幣驅逐良幣\n\n而且專業人士都會管控好自己的上站頻率\n\n往往是一個星期\n\n甚至是一個月才上站一次\n\n只有刻意想要洗風向的惡意人士\n\n才會維持天天上站的網路成癮現象\n\n自己想一想，批踢踢沒了專業人士的專業文\n\n批踢踢還剩下什麼？\n\n不要跟我說什麼政治正確\n\n現實社會中，聰明人絕對不會讓外人知道自己支持誰\n\n只會跟你說自己是中間選民\n\n永遠都是投票日當天見真章\n\n如果硬要人家表態\n\n他們會叫你去看無情真實的未來事件網站\n\n不然就去看未來事件交易所\n\n看完就知道正確答案了\n\n批踢踢搞成這樣\n\n十足像個癌末病人\n\n--\n", 
        "DownVote": 3
    }, 
    {
        "Title": "[問卦] 有沒有台大EDA電子所的八卦", 
        "Author": "sunarmed", 
        "UpVote": 7, 
        "NoVote": 0, 
        "Content": "\n\n各位八卦板 年薪300萬up 30CM 33D Cup 的大大大家好\n\n全世界台灣價值最高的研究所----台大電子所\n\n打造無數勇健活跳的肝\n\n到竹科和台GG輪班創造全台最高經濟產值\n\n就在電子所有個丙組EDA組\n\n聽說是個偏軟體演算法的組別\n\n軟硬通吃豈非制霸天下\n\n不過我有朋友在裡面說天天meeting到SAN值歸零\n\n只能看南極撫慰受傷的心靈\n\n有沒有八卦?\n\n\n--\n", 
        "DownVote": 0
    }
]