[
    {
        "Title": "[新聞]陝西安康強徵地 數十人棒毆村民 奪扔1歲童", 
        "Author": "clarencelin", 
        "UpVote": 9, 
        "NoVote": 6, 
        "Content": "\n1.媒體來源:大紀元\n\n2.完整新聞標題:陝西安康強徵地 數十人棒毆村民 奪扔1歲童\n\n3.完整新聞內文:【大紀元2018年05月27日訊】（大紀元記者李新安報導）\n近日，陝西省安康市被曝", 
        "DownVote": 2
    }, 
    {
        "Title": "[問卦] DAN DAN心漸漸被你迷惑", 
        "Author": "HDSM", 
        "UpVote": 21, 
        "NoVote": 11, 
        "Content": "\n安安\n\n大給賀阿!!!\n\n是降的拉\n\n本肥想問問呀\n\n是不是總有一個人會讓人感受到\n\nDAN DAN 心漸漸被你迷惑\n\n最後 只注意著你的事情而已\n\n如果肥宅們在她遇到困難時說Hold My Hand\n\n會不會大加分\n\n可以嘗試告白看看了o'_'o???\n\n--\n", 
        "DownVote": 1
    }, 
    {
        "Title": "Re: [問卦] 為什麼台大一堆情殺相關案件?", 
        "Author": "gigi2001", 
        "UpVote": 0, 
        "NoVote": 0, 
        "Content": "\n1998\n\n台大潑酸事件 勾起駭人的清大「王水」溶屍案回憶...\n", 
        "DownVote": 0
    }, 
    {
        "Title": "[新聞] 高雄市長民調 陳其邁領先韓國瑜31％", 
        "Author": "opica", 
        "UpVote": 103, 
        "NoVote": 84, 
        "Content": "\n愛河性愛摩天輪\n高雄蓋迪士尼\n\n這樣的政見怎麼沒人支持呢？\n\n自由\n\n高雄市長民調 陳其邁領先韓國瑜31％\n\n根據新台灣國策智庫委託趨勢民意調查公司，5月14日至17日所做高雄市長選舉支持度最\n新民調顯示，民進黨陳其邁支持度52%，國民黨韓國瑜支持度21%，陳其邁支持度大幅領先\n韓國瑜31個百分點。\n\n年底高雄市長選舉，國民黨推派韓國瑜挑戰民進黨提名的陳其邁，從民調數據分析，20~3\n9歲有47.1%支持陳其邁，勝過韓國瑜的20.1%，顯示年輕族群也較偏向陳其邁。\n\n在政黨傾向上，陳其邁除民進黨選民中獲得89.1%超高支持度，同時獲得時代力量支持者\n高達70.1%支持；相較韓國瑜獲得國民黨選民61.6%、親民黨選民44.9%的主要支持，陳其\n邁尚獲得國民黨22%、親民黨30.2%、兩大黨以外其他政黨45.8%的支持，而韓國瑜在泛綠\n支持者中，僅獲得民進黨選民3%的支持。\n\n陳其邁在不偏任何政黨選民部份，也有39.2%的相當支持度，陳其邁明顯囊括跨黨派選票\n，從數據也看出高雄市的綠軍整合。\n\n而國民黨認為韓國瑜是接地氣的候選人，但外界對於韓國瑜的空降及對高雄市的熟悉度仍\n待觀察。\n\n從分析顯示，不表態率僅16.4%，解讀陳其邁在高雄市長選舉領先態勢趨向明確化，選情\n相對穩固。\n\n趨勢民意調查係於5月14日至17日下午14:00~17:30、晚上18:30~22:00執行，以電腦輔助\n電話訪問系統（GATI），進行住宅電話調查，完成819份有效樣本，在95%信心水準下，抽\n樣誤差為正負3.4個百分點。\n\n", 
        "DownVote": 25
    }, 
    {
        "Title": "[問卦]驚！羅馬的首都不是羅馬！？", 
        "Author": "ccyaztfe", 
        "UpVote": 2, 
        "NoVote": 8, 
        "Content": "\n驚！\n\n羅馬帝國的首都居然不是在羅馬，而是在拉文納！！！\n\n這個事實讓全球60E人都驚呆了！\n\n就好像玉米蛋餅沒有玉米\n\n蔥花蛋沒有蔥\n\n牛肉麵沒有牛肉一樣\n\n羅馬帝國首都不在羅馬，為什麼還會叫羅馬帝國！？\n\n\n其實這是有著淵遠流長的歷史的0_0\n\n最一開始羅馬首都確實是羅馬\n\n然而隨著時代的變遷，羅馬已經不在具備優勢了\n\n為了商業考量軍事考量，遷都到別的地方\n\n之後羅馬再也沒有變成首都了OAO\n\n不過元老院還是留在羅馬喔  诶嘿☆(ゝω●)\n\n\n\n這樣各位肥宅知道了嗎？\n\n又幫大家上了一課，我真是貢獻良多0.0\n\n真應該給我多一點P幣以玆鼓勵的><\n\n--\n", 
        "DownVote": 7
    }, 
    {
        "Title": "[問卦] 安達祐實cosplay幼稚園生 小學生的八卦?", 
        "Author": "hmt17", 
        "UpVote": 32, 
        "NoVote": 15, 
        "Content": "\n\n晚安 是這樣的\n\n就是剛才的閒聊節目，來賓是36歲童顏女優\n\n安達祐實啦 不知道是要宣傳啥東東就來了\n\n慣例到企劃單元 安達就cosplay扮演各年齡層的學生\n\n像是...4歲幼稚園生\n", 
        "DownVote": 2
    }, 
    {
        "Title": "[新聞] 男友持刀闖住處　女子遭殺害身亡", 
        "Author": "OdaTakeda", 
        "UpVote": 30, 
        "NoVote": 37, 
        "Content": "\n1.媒體來源:\nAPPLE\n\n2.完整新聞標題:\n男友持刀闖住處　女子遭殺害身亡\n\n3.完整新聞內文:\n\n今晚8時許，台北市警方接獲報案指稱，中山北路三段某大樓內發生命案，警方趕抵後發\n現1名邱姓女子（年約27歲）身有刀傷躺臥血泊，經緊急送醫後仍不治身亡。警方在現場\n逮捕疑似酒醉，精神恍惚的廖姓男友（27歲），初步了解，廖男疑因與邱女感情糾紛起爭\n執，憤而殺害女友。由於廖男意識不清，警方先將他帶回警局了解案情，並封鎖現場以利\n進一步鑑識。\n\n警方表示，今天晚間7時許，獲報有人持刀進入住宅，趕抵現場卻大門深鎖，敲門都無人\n回應，消防局救護人員到場再度敲門後，嫌犯廖男（27歲）開門，進入查看發現邱姓女友\n（26歲）倒臥浴室外，身上有明顯刀傷，現場血跡斑斑，救護人員立即上前檢傷，邱女已\n無呼吸脈搏，立即給予急救後送醫，但送醫後仍宣告不治，警方隨後在現場床邊發現一把\n水果刀，上面沾滿血跡，立即將廖男逮捕，並通知鑑識人員到場採證及調閱監視器，目前\n廖男帶回派出所後因為酒醉意識不清，等廖男酒醒訊後，會依殺人罪嫌送辦。（突發中心\n／台北報導）\n\n4.完整新聞連結 (或短網址):\n", 
        "DownVote": 5
    }, 
    {
        "Title": "[問卦] 鯰魚老杯杯的謎語到底是什麼", 
        "Author": "GentleJena", 
        "UpVote": 1, 
        "NoVote": 1, 
        "Content": "\n如題啦\n\n最近從屁眼穿過漫長的腸之旅\n\n終於來到了胃\n\n遇見了一個只會出謎語的鯰魚老杯杯\n\n要回答他的謎語才能夠脫困\n\n可是那個死老害什麼都不說\n\n就把我綁上一個裝置\n\n到底謎語是什麼啦\n\n有沒有八卦\n\n--\n你沒有迷路，你將踏上成為魔法師的道路\n\n這很艱辛，但是你的長相可以幫助你\n\n--\n", 
        "DownVote": 0
    }, 
    {
        "Title": "[問卦] 現在不吹冷氣以後是不是吹不到了？", 
        "Author": "just10263", 
        "UpVote": 2, 
        "NoVote": 3, 
        "Content": "\n古時 唐伯虎 喜歡吃紅燒雞翅\n他說過：「如果現在不吃  以後沒機會再吃」\n\n肥仔我很喜歡吹冷氣  聽說電越來越少了\n是不是要趕快吹冷氣\n不然以後沒有電可用 就吹不到了？\n\n--\n", 
        "DownVote": 0
    }, 
    {
        "Title": "Re: [問卦] 男人不壞 女人不愛是真的嗎?", 
        "Author": "nicholas0406", 
        "UpVote": 1, 
        "NoVote": 4, 
        "Content": "\nPTT肥宅 有夠可憐\n\n看到人家搞家暴 既是煙毒犯 又有暴力傾向\n\n就覺得這種人渣都有女友\n\n但我卻沒有\n\n一定是台女都愛渣男\n\n男人不壞 女人不愛\n\n\n所謂的壞 不是叫你去作奸犯科 殺人放火 當個匪類\n\n而是個性上不要唯唯諾諾的\n\n我看過一堆阿宅 真的天生就是工具人的命\n\n幫女森修電腦 不求回報 真的阿呆\n\n女森：你可以幫我個忙嗎 ? 幫我修電腦\n\n肥宅：好好好 ~ (像條哈巴狗 很開心猛點頭)\n\n女森：謝謝你唷 ~ 啾咪\n\n\n有的肥宅搞不好 妹子只是要組I5 他還自掏腰包 幫她升級到I7\n\n妹子只要GTX1060玩吃雞  肥宅還會自動幫她升級到GTX1070\n\n\n稍微懂女森的 就不會當免費的工具人\n\n通常都會說 幫妳修電腦 但是妳要請我吃飯\n\n於是下一次的約會 就這樣很自然地展開了\n\n\n但是死肥宅通常修完電腦後 就沒下次了\n\n除非等妹子下次電腦壞了 才有可能再找你\n\n\n題外話\n\n我覺得馬子狗比工具人更可悲 ~ 更讓我看不起\n\n--\n", 
        "DownVote": 1
    }, 
    {
        "Title": "[問卦] 有沒有大家都不愛看公告水桶文的八卦?", 
        "Author": "RandyMarsh", 
        "UpVote": 4, 
        "NoVote": 8, 
        "Content": "\n以前玩八卦板，最喜歡的就是看公告水桶文\n\n看看板主的判罰標準尺度\n\n抓板主的好球帶\n\n然後不斷的測試底線\n\n感覺十分有趣\n\n所以每篇公告水桶文都會仔細的看完全文\n\n\n\n但是不是現在的人都不愛閱讀，\n\n公告水桶文都沒有人要看了\n\n就算有發錢，但如果沒有把發錢寫在標題或是文章一開始\n\n藏在中間當大秘寶，也都不會有人看到\n\n\n\n\n有沒有現在公告水桶文都沒有人要看\n\n就算在文章中間說要發錢，也沒有人要看的八卦阿Q_Q\n\n\n--\n", 
        "DownVote": 2
    }, 
    {
        "Title": "Re: [問卦] 台灣最近一堆殺人案件?是怎麼了?", 
        "Author": "dispptt", 
        "UpVote": 3, 
        "NoVote": 4, 
        "Content": "\n因為民進洞的廢死、人權政策大成功啊\n\n反正又不會判死\n\n所以一個比一個還猛XDDDDDDDD 看你要分屍還是開17槍 任君選擇\n\n\n\n你兩蔣時代試看看\n\n以前要是這樣有重大刑案 當天晚上11點 舊三台一定會直播槍決死刑犯10個來殺雞儆猴\n\n\n台灣 已經被民進黨弄爛摟\n\n台灣只會越來越亂而已 相信我 自求多福吧各位\n\n--\n", 
        "DownVote": 1
    }, 
    {
        "Title": "[問卦] 有沒有蘿莉驚奇隊長的八卦？", 
        "Author": "k44521272", 
        "UpVote": 10, 
        "NoVote": 3, 
        "Content": "\n\n各位鄉民好︰\n", 
        "DownVote": 5
    }, 
    {
        "Title": "[問卦] 台灣有台積電 中國有自己前端的技術？", 
        "Author": "q0000000", 
        "UpVote": 35, 
        "NoVote": 22, 
        "Content": "\n\n台灣有台積電技術佔住世界首位\n而中國那麼大人口這麼多\n\n那中國有什麼技術是佔住世界前端的啊？\n高鐵車輛製造技術？船隻製造技術？核電廠製造技術？\n\n台灣有台積電 中國有自己前端的技術嗎？\n\n\n--\n", 
        "DownVote": 4
    }, 
    {
        "Title": "Re: [問卦] 為什麼中醫師都鼓勵多吃米少吃麵粉", 
        "Author": "z0953781935", 
        "UpVote": 3, 
        "NoVote": 2, 
        "Content": "\n\n中醫什麼理論我不知道，\n麵包這東西已經被很多營養師醫生說不健康了，\n危害最大的就是反式脂肪跟糖份，就麵粉來說本身也沒有什麼營養，\n還有麵包在烤的過程中多少也會有不好的物質產生\n\n米應該是沒什麼加工跟添加物，所以醫生推薦吧\n\n\n講實在話，既然麵包那麼貴又不太健康，我寧願吃洋芋片雞排吃到掛掉\n\n\n\n\n\n\n\n--\n我老婆1\n", 
        "DownVote": 0
    }, 
    {
        "Title": "[問卦] 有沒有分屍案不斷更新的八卦？", 
        "Author": "kyouya", 
        "UpVote": 5, 
        "NoVote": 5, 
        "Content": "\n\n恐怖台男分屍台大女友後畏罪上吊死亡\n\n一句話可以說完的事情是有什麼可以更新的啦？\n\n到底要更新什麼？\n\n有沒有卦??\n-----\nSent from JPTT on my iPhone\n\n--\n", 
        "DownVote": 1
    }, 
    {
        "Title": "[問卦] 有王者基多拉的粉絲嗎？", 
        "Author": "carrey1994", 
        "UpVote": 7, 
        "NoVote": 2, 
        "Content": "\n\n常常被東寶的怪獸一哥哥吉拉叫去泡茶\n\n外型霸氣又帥\n\n全身金色又是三頭飛龍\n\n還有好朋友魔斯拉\n\n之後好像又要再次登場\n\n有王者基多拉的粉絲嗎？\n-----\nSent from JPTT on my iPhone\n\n--\n", 
        "DownVote": 0
    }, 
    {
        "Title": "[問卦] 要陪美紀散步多久?", 
        "Author": "ralfeistein", 
        "UpVote": 5, 
        "NoVote": 4, 
        "Content": "\n\n\n這個周末吃試了好多我家", 
        "DownVote": 3
    }, 
    {
        "Title": "[問卦] 異性戀都很愛殺掉另一半嗎?", 
        "Author": "BetterFight", 
        "UpVote": 12, 
        "NoVote": 13, 
        "Content": "\n最近拳擊教練分屍案轟轟烈烈\n\n新聞都還沒退燒\n\n馬上就來個酒店妹陳屍案\n\n異性戀到底發生什麼事了\n\n為什麼一直殺另一半?\n\n--\n", 
        "DownVote": 5
    }
]